{
    "Rating": {
        "Offers": "4.43",
        "Payment": "4.43",
        "Tracking": "4.14",
        "Support": "4.29"
    },
    "Contact": {
        "Email": "show email",
        "Phone": "n/a",
        "Twitter": "n/a",
        "Facebook": "Fanpage"
    },
    "Tracking": {
        "Tracking Domain(s)": "n/a"
    },
    "Offers": {
        "Commission Type": [
            "CPA",
            " Revshare"
        ]
    },
    "Network Extra": [
        "Mobile Optimized",
        " Incentive Friendly"
    ],
    "Payment": {
        "Payment Frequency": [
            "Weekly"
        ],
        "Payment Delay": [
            "Net 7 ",
            " Net 15"
        ],
        "Payment Method": [
            " MethodWebMoney",
            " Capitalist"
        ]
    }
}